alphonse/__init__.py
alphonse/crud.py
alphonse/db_manager.py
alphonse/sql_constructor.py
alphonse/utilities.py
alphonse-0.1.4.dist-info/LICENSE.txt
alphonse-0.1.4.dist-info/METADATA
alphonse-0.1.4.dist-info/WHEEL
alphonse-0.1.4.dist-info/top_level.txt
alphonse-0.1.4.dist-info/RECORD
