Metadata-Version: 2.1
Name: alphonse
Version: 0.1.4
Summary: A wrapper around SQLAlchemy to make it easier to make more complex queries
Author: Jackson Prince
Maintainer: Jackson Prince
License: Copyright (c) 2024 Wavelynx Technologies Corporation
Project-URL: Source, https://gitlab.com/WaveLynxTech/alphonse
Keywords: python,sqlalchemy
Classifier: Development Status :: 3 - Alpha
Classifier: Intended Audience :: Developers
Classifier: License :: OSI Approved :: MIT License
Classifier: Programming Language :: Python :: 3
Requires-Python: >=3.8
License-File: LICENSE.txt
Requires-Dist: SQLAlchemy>=1.4.41
Requires-Dist: solidipy>=0.3.1
Provides-Extra: test
Requires-Dist: pytest; extra == "test"
Requires-Dist: coverage; extra == "test"
Requires-Dist: SQLAlchemy; extra == "test"
Requires-Dist: solidipy; extra == "test"
